dataclouder_core/__init__.py
dataclouder_core/db/mongo.py
dataclouder_core/exception.py
dataclouder_core/models/models.py
dataclouder_core-0.0.5.dist-info/METADATA
dataclouder_core-0.0.5.dist-info/WHEEL
dataclouder_core-0.0.5.dist-info/RECORD
