Metadata-Version: 2.3
Name: dataclouder-core
Version: 0.0.5
Summary: A library Core for dataclouder projects
Author: adamo figueroa
Author-email: adamo@dataclouder.com
Requires-Python: >=3.11
Classifier: Programming Language :: Python :: 3
Classifier: Programming Language :: Python :: 3.11
Classifier: Programming Language :: Python :: 3.12
Classifier: Programming Language :: Python :: 3.13
Requires-Dist: fastapi (>=0.100.0)
Requires-Dist: pydantic-ai (>=0.0.19)
